resp_server/__init__.py
resp_server/config.py
resp_server/main.py
resp_server/core/__init__.py
resp_server/core/command_execution.py
resp_server/core/context.py
resp_server/core/datastore.py
resp_server/core/server.py
resp_server/protocol/__init__.py
resp_server/protocol/constants.py
resp_server/protocol/resp.py
resp_server-0.2.3.dist-info/entry_points.txt
resp_server-0.2.3.dist-info/licenses/LICENSE
resp_server-0.2.3.dist-info/WHEEL
resp_server-0.2.3.dist-info/METADATA
resp_server-0.2.3.dist-info/RECORD
