Metadata-Version: 2.4
Name: resp-server
Version: 0.2.3
Summary: A lightweight, embeddable, pure-Python Redis-compatible server for testing.
Keywords: redis,server,embedded,testing,mock
Author-email: Vivek Dagar <vivek@example.com>
Requires-Python: >=3.9
Classifier: Development Status :: 3 - Alpha
Classifier: Intended Audience :: Developers
Classifier: License :: OSI Approved :: MIT License
Classifier: Programming Language :: Python :: 3
Classifier: Topic :: Software Development :: Testing
Classifier: Topic :: Database
License-File: LICENSE
Requires-Dist: click
Project-URL: Home, https://github.com/vivekdagar/resp-server
